[
    {
        "like_count": 64984,
        "comment_count": 64984,
        "caption": "The king on a walkabout.\n-\n\ud83c\udfa5 @primuscat\n-\n@meowed #cat #majestictail #9gag",
        "id": "1948017988724710605",
        "short_code": "BsIwAoqAdzN",
        "hash_tags": [
            "majestictail",
            "cat",
            "9gag"
        ],
        "taken_at": 1546441881,
        "media_urls": [
            "https://instagram.fhkg1-1.fna.fbcdn.net/vp/a3d5c71dafd314fcd1538eca9181d88c/5C2FCFBF/t50.2886-16/49787800_945798905624870_7435423322428407808_n.mp4?_nc_ht=instagram.fhkg1-1.fna.fbcdn.net"
        ],
        "username": "9gag"
    },
    {
        "like_count": 316132,
        "comment_count": 316132,
        "caption": "Grandma is the queen of trick shots!\nBy @smoothsmith8\n-\n#9gag #trickshots",
        "id": "1947951873969458472",
        "short_code": "BsIg-ifgY0o",
        "hash_tags": [
            "trickshots",
            "9gag"
        ],
        "taken_at": 1546434037,
        "media_urls": [
            "https://instagram.fhkg1-1.fna.fbcdn.net/vp/06f86bbafda1d7253c4e61907ba6dda1/5C2FDAA5/t50.2886-16/49888246_1998939586880728_8495841397667004416_n.mp4?_nc_ht=instagram.fhkg1-1.fna.fbcdn.net"
        ],
        "username": "9gag"
    },
    {
        "like_count": 1044863,
        "comment_count": 1044863,
        "caption": "Don\u2019t you ever stop \ud83d\ude3e Follow @couple for more #couplegoals .\u2800\n-\u2800\n\u270f @bonniepangart\u2800\n-\u2800\n#couple #relationship #relationshipgoals #comic #petting #stop",
        "id": "1947921966410525555",
        "short_code": "BsIaLU6FGtz",
        "hash_tags": [
            "relationship",
            "couple",
            "couplegoals",
            "relationshipgoals",
            "stop",
            "petting",
            "comic"
        ],
        "taken_at": 1546430415,
        "media_urls": [
            "https://instagram.fhkg1-1.fna.fbcdn.net/vp/bd2fe641340d232aed9ab831f36702aa/5CD83488/t51.2885-15/fr/e15/s1080x1080/47581265_632747737140513_6304648313623756796_n.jpg?_nc_ht=instagram.fhkg1-1.fna.fbcdn.net&ig_cache_key=MTk0NzkyMTk2NjQxMDUyNTU1NQ%3D%3D.2"
        ],
        "username": "9gag"
    }
]
